pyrabbit2/__init__.py
pyrabbit2/api.py
pyrabbit2/http.py
pyrabbit2-1.0.7.dist-info/LICENSE
pyrabbit2-1.0.7.dist-info/METADATA
pyrabbit2-1.0.7.dist-info/WHEEL
pyrabbit2-1.0.7.dist-info/top_level.txt
pyrabbit2-1.0.7.dist-info/RECORD
