Metadata-Version: 2.1
Name: pyrabbit2
Version: 1.0.7
Summary: A Pythonic interface to the RabbitMQ Management HTTP API
Home-page: https://github.com/deslum/pyrabbit2
Author: Brian K. Jones, Yuri Bukatkin
Author-email: bkjones@gmail.com, windowod@gmail.com
License: MIT
Download-URL: https://github.com/deslum/pyrabbit2/archive/master.zip
Keywords: python http amqp rabbit rabbitmq management
Platform: UNKNOWN
Classifier: Intended Audience :: Developers
Classifier: License :: OSI Approved :: MIT License
Classifier: Natural Language :: English
Classifier: Programming Language :: Python
Classifier: Programming Language :: Python :: 2
Classifier: Programming Language :: Python :: 2.6
Classifier: Programming Language :: Python :: 2.7
Classifier: Programming Language :: Python :: 3.5
Classifier: Programming Language :: Python :: 3.6
Classifier: Topic :: Internet :: WWW/HTTP
Classifier: Topic :: Software Development :: Libraries :: Python Modules
Requires-Dist: requests
